{
  "topics": [
    "development",
    "travel",
    "work",
    "articles",
    "tech",
    "general"
  ],
  "news": [
    {
      "date": 1757704759,
      "title": "Test news piece",
      "description": "This thing is test, do not worry",
      "pic": {
        "url": "assets/dashboard-project.png",
        "local": true
      },
      "content": {
        "type": "link",
        "body": "https://link.puzzak.page/?dashboard"
      },
      "body": "test.md",
      "tags": "general, article"
    }
  ]
}